xian_bds/bds.py
xian_bds/database.py
xian_bds/sql.py
xian_bds-0.1.2.dist-info/METADATA
xian_bds-0.1.2.dist-info/WHEEL
xian_bds-0.1.2.dist-info/RECORD
